redbox/__init__.py
redbox/_version.py
redbox/box.py
redbox/testing.py
redbox/models/__init__.py
redbox/models/attachment.py
redbox/models/mailbox.py
redbox/models/message.py
redbox/query/__init__.py
redbox/query/query.py
redbox/tests/__init__.py
redbox/tests/conftest.py
redbox/tests/test_fetch.py
redbox/tests/test_query.py
redbox/tests/test_search.py
redbox/utils/__init__.py
redbox/utils/inspector.py
redbox-0.2.1.dist-info/LICENSE
redbox-0.2.1.dist-info/METADATA
redbox-0.2.1.dist-info/WHEEL
redbox-0.2.1.dist-info/top_level.txt
redbox-0.2.1.dist-info/RECORD
