Metadata-Version: 2.1
Name: redbox
Version: 0.2.1
Summary: Email box reading library
Home-page: https://github.com/Miksus/red-box.git
Author: Mikael Koli
Author-email: koli.mikael@gmail.com
Classifier: Development Status :: 4 - Beta
Classifier: Topic :: Communications :: Email
Classifier: Operating System :: OS Independent
Classifier: License :: OSI Approved :: MIT License
Classifier: Programming Language :: Python :: 3
Classifier: Programming Language :: Python :: 3.6
Classifier: Programming Language :: Python :: 3.7
Classifier: Programming Language :: Python :: 3.8
Classifier: Programming Language :: Python :: 3.9
Classifier: Programming Language :: Python :: 3.10
Classifier: Intended Audience :: Developers
Classifier: Intended Audience :: Customer Service
Classifier: Intended Audience :: Financial and Insurance Industry
Requires-Python: >=3.6.0
License-File: LICENSE
Requires-Dist: pydantic
